[
    {
        "Material Name":  "alum",
        "Tags":  [
                     "Materials / Textile Mordant"
                 ]
    },
    {
        "Material Name":  "ephedra",
        "Tags":  [
                     "Materials / Natural Materials / Food / Herb"
                 ]
    },
    {
        "Material Name":  "foxglove",
        "Tags":  [
                     "Materials / Natural Materials / Food / Herb"
                 ]
    },
    {
        "Material Name":  "gut",
        "Tags":  [
                     "Materials / Animal Product",
                     "Materials / Animal Product / Butchery Output / Crafting Animal Product"
                 ]
    },
    {
        "Material Name":  "henbane",
        "Tags":  [
                     "Materials / Natural Materials / Food / Herb"
                 ]
    },
    {
        "Material Name":  "mandrake",
        "Tags":  [
                     "Materials / Natural Materials / Food / Herb"
                 ]
    },
    {
        "Material Name":  "yarrow",
        "Tags":  [
                     "Materials / Natural Materials / Food / Herb"
                 ]
    }
]
